[
  {
    "id": 1,
    "date": "2026-05-30 00:00",
    "time": "00:00",
    "entity_a": "Hurricanes",
    "entity_b": "Canadiens",
    "venue": "Lenovo Center",
    "a_win_prob": 73.6,
    "draw_prob": 0.0,
    "b_win_prob": 26.4,
    "prediction": "Home Win",
    "actual_result": "Not Played",
    "score_a": null,
    "score_b": null,
    "is_correct": null,
    "confidence": 73.6,
    "confidence_level": "High",
    "elo_a": 1521,
    "elo_b": 1479,
    "elo_diff": 42,
    "colley_a": 1673,
    "colley_b": 1385,
    "form_a": 90.0,
    "form_b": 20.0,
    "odds_available": true,
    "odds_source": "espn_embedded",
    "sources": {
      "elo": {
        "a": 63.6,
        "d": 0.0,
        "b": 36.4
      },
      "colley": {
        "a": 87.8,
        "d": 0.0,
        "b": 12.2
      },
      "form": {
        "a": 98.3,
        "d": 0.0,
        "b": 1.7
      },
      "odds": {
        "a": 67.5,
        "d": 0.0,
        "b": 32.5
      }
    },
    "weights_used": {
      "elo": 0.4,
      "colley": 0.15,
      "form": 0.15,
      "odds": 0.3
    },
    "day_of_week": "Saturday",
    "week_number": 22,
    "year": 2026,
    "month": 5,
    "espn_odds": {
      "home_ml": "-238",
      "away_ml": "+195",
      "spread": "CAR -238",
      "over_under": 5.5
    }
  },
  {
    "id": 2,
    "date": "2026-05-31 04:00",
    "time": "04:00",
    "entity_a": "Canadiens",
    "entity_b": "Hurricanes",
    "venue": "Bell Centre",
    "a_win_prob": 34.5,
    "draw_prob": 0.0,
    "b_win_prob": 65.5,
    "prediction": "Away Win",
    "actual_result": "Not Played",
    "score_a": null,
    "score_b": null,
    "is_correct": null,
    "confidence": 65.5,
    "confidence_level": "Medium",
    "elo_a": 1479,
    "elo_b": 1521,
    "elo_diff": -42,
    "colley_a": 1385,
    "colley_b": 1673,
    "form_a": 20.0,
    "form_b": 90.0,
    "odds_available": false,
    "odds_source": null,
    "sources": {
      "elo": {
        "a": 51.9,
        "d": 0.0,
        "b": 48.1
      },
      "colley": {
        "a": 20.7,
        "d": 0.0,
        "b": 79.3
      },
      "form": {
        "a": 1.7,
        "d": 0.0,
        "b": 98.3
      },
      "odds": null
    },
    "weights_used": {
      "elo": 0.5714285714285714,
      "colley": 0.21428571428571425,
      "form": 0.21428571428571425,
      "odds": 0.0
    },
    "day_of_week": "Sunday",
    "week_number": 22,
    "year": 2026,
    "month": 5
  },
  {
    "id": 3,
    "date": "2026-06-03 00:00",
    "time": "00:00",
    "entity_a": "Hurricanes",
    "entity_b": "Canadiens",
    "venue": "Lenovo Center",
    "a_win_prob": 76.2,
    "draw_prob": 0.0,
    "b_win_prob": 23.8,
    "prediction": "Home Win",
    "actual_result": "Not Played",
    "score_a": null,
    "score_b": null,
    "is_correct": null,
    "confidence": 76.2,
    "confidence_level": "High",
    "elo_a": 1521,
    "elo_b": 1479,
    "elo_diff": 42,
    "colley_a": 1673,
    "colley_b": 1385,
    "form_a": 90.0,
    "form_b": 20.0,
    "odds_available": false,
    "odds_source": null,
    "sources": {
      "elo": {
        "a": 63.6,
        "d": 0.0,
        "b": 36.4
      },
      "colley": {
        "a": 87.8,
        "d": 0.0,
        "b": 12.2
      },
      "form": {
        "a": 98.3,
        "d": 0.0,
        "b": 1.7
      },
      "odds": null
    },
    "weights_used": {
      "elo": 0.5714285714285714,
      "colley": 0.21428571428571425,
      "form": 0.21428571428571425,
      "odds": 0.0
    },
    "day_of_week": "Wednesday",
    "week_number": 23,
    "year": 2026,
    "month": 6
  }
]