[
  {
    "id": 1,
    "date": "2026-05-17 19:00",
    "time": "19:00",
    "entity_a": "Brest",
    "entity_b": "Angers",
    "venue": "Stade Francis-Le Blé",
    "a_win_prob": 26.2,
    "draw_prob": 17.8,
    "b_win_prob": 56.0,
    "prediction": "Away Win",
    "actual_result": "Not Played",
    "score_a": null,
    "score_b": null,
    "is_correct": null,
    "confidence": 56.0,
    "confidence_level": "Medium",
    "elo_a": 1473.646624,
    "elo_b": 1498.2637489335066,
    "elo_diff": -25,
    "colley_a": 1200,
    "colley_b": 1520,
    "form_a": 0.0,
    "form_b": 50.0,
    "odds_available": false,
    "sources": {
      "elo": {
        "a": 42.6,
        "d": 23.6,
        "b": 33.8
      },
      "colley": {
        "a": 16.5,
        "d": 12.0,
        "b": 71.5
      },
      "form": {
        "a": 4.7,
        "d": 12.0,
        "b": 83.3
      },
      "odds": null
    },
    "weights_used": {
      "elo": 0.5,
      "colley": 0.2142857142857143,
      "form": 0.28571428571428575,
      "odds": 0.0
    },
    "day_of_week": "Sunday",
    "week_number": 20,
    "year": 2026,
    "month": 5
  },
  {
    "id": 2,
    "date": "2026-05-17 19:00",
    "time": "19:00",
    "entity_a": "Lille",
    "entity_b": "Auxerre",
    "venue": "Decathlon Arena - Stade Pierre-Mauroy",
    "a_win_prob": 44.0,
    "draw_prob": 23.1,
    "b_win_prob": 32.9,
    "prediction": "Home Win",
    "actual_result": "Not Played",
    "score_a": null,
    "score_b": null,
    "is_correct": null,
    "confidence": 44.0,
    "confidence_level": "Low",
    "elo_a": 1516.8310052364159,
    "elo_b": 1511.059919293563,
    "elo_diff": 6,
    "colley_a": 1669,
    "colley_b": 1669,
    "form_a": 100.0,
    "form_b": 100.0,
    "odds_available": false,
    "sources": {
      "elo": {
        "a": 47.0,
        "d": 21.8,
        "b": 31.2
      },
      "colley": {
        "a": 46.2,
        "d": 22.1,
        "b": 31.7
      },
      "form": {
        "a": 37.0,
        "d": 26.0,
        "b": 37.0
      },
      "odds": null
    },
    "weights_used": {
      "elo": 0.5,
      "colley": 0.2142857142857143,
      "form": 0.28571428571428575,
      "odds": 0.0
    },
    "day_of_week": "Sunday",
    "week_number": 20,
    "year": 2026,
    "month": 5
  },
  {
    "id": 3,
    "date": "2026-05-17 19:00",
    "time": "19:00",
    "entity_a": "Lorient",
    "entity_b": "Le Havre AC",
    "venue": "Stade du Moustoir - Yves Allainmat",
    "a_win_prob": 68.2,
    "draw_prob": 16.0,
    "b_win_prob": 15.8,
    "prediction": "Home Win",
    "actual_result": "Not Played",
    "score_a": null,
    "score_b": null,
    "is_correct": null,
    "confidence": 68.2,
    "confidence_level": "Medium",
    "elo_a": 1517.52499504,
    "elo_b": 1482.8255048608,
    "elo_diff": 35,
    "colley_a": 1669,
    "colley_b": 1279,
    "form_a": 100.0,
    "form_b": 0.0,
    "odds_available": false,
    "sources": {
      "elo": {
        "a": 51.2,
        "d": 20.0,
        "b": 28.8
      },
      "colley": {
        "a": 82.0,
        "d": 12.0,
        "b": 6.0
      },
      "form": {
        "a": 87.7,
        "d": 12.0,
        "b": 0.3
      },
      "odds": null
    },
    "weights_used": {
      "elo": 0.5,
      "colley": 0.2142857142857143,
      "form": 0.28571428571428575,
      "odds": 0.0
    },
    "day_of_week": "Sunday",
    "week_number": 20,
    "year": 2026,
    "month": 5
  },
  {
    "id": 4,
    "date": "2026-05-17 19:00",
    "time": "19:00",
    "entity_a": "Lyon",
    "entity_b": "Lens",
    "venue": "Groupama Stadium",
    "a_win_prob": 28.2,
    "draw_prob": 18.4,
    "b_win_prob": 53.4,
    "prediction": "Away Win",
    "actual_result": "Not Played",
    "score_a": null,
    "score_b": null,
    "is_correct": null,
    "confidence": 53.4,
    "confidence_level": "Medium",
    "elo_a": 1487.26,
    "elo_b": 1498,
    "elo_diff": -11,
    "colley_a": 1279,
    "colley_b": 1492,
    "form_a": 0.0,
    "form_b": 66.7,
    "odds_available": false,
    "sources": {
      "elo": {
        "a": 44.6,
        "d": 22.7,
        "b": 32.7
      },
      "colley": {
        "a": 24.8,
        "d": 17.1,
        "b": 58.1
      },
      "form": {
        "a": 1.9,
        "d": 12.0,
        "b": 86.1
      },
      "odds": null
    },
    "weights_used": {
      "elo": 0.5,
      "colley": 0.2142857142857143,
      "form": 0.28571428571428575,
      "odds": 0.0
    },
    "day_of_week": "Sunday",
    "week_number": 20,
    "year": 2026,
    "month": 5
  },
  {
    "id": 5,
    "date": "2026-05-17 19:00",
    "time": "19:00",
    "entity_a": "Marseille",
    "entity_b": "Rennes",
    "venue": "Stade Vélodrome",
    "a_win_prob": 43.9,
    "draw_prob": 23.1,
    "b_win_prob": 33.0,
    "prediction": "Home Win",
    "actual_result": "Not Played",
    "score_a": null,
    "score_b": null,
    "is_correct": null,
    "confidence": 43.9,
    "confidence_level": "Low",
    "elo_a": 1517.1744951392,
    "elo_b": 1512.4852,
    "elo_diff": 5,
    "colley_a": 1669,
    "colley_b": 1669,
    "form_a": 100.0,
    "form_b": 100.0,
    "odds_available": false,
    "sources": {
      "elo": {
        "a": 46.8,
        "d": 21.8,
        "b": 31.4
      },
      "colley": {
        "a": 46.2,
        "d": 22.1,
        "b": 31.7
      },
      "form": {
        "a": 37.0,
        "d": 26.0,
        "b": 37.0
      },
      "odds": null
    },
    "weights_used": {
      "elo": 0.5,
      "colley": 0.2142857142857143,
      "form": 0.28571428571428575,
      "odds": 0.0
    },
    "day_of_week": "Sunday",
    "week_number": 20,
    "year": 2026,
    "month": 5
  },
  {
    "id": 6,
    "date": "2026-05-17 19:00",
    "time": "19:00",
    "entity_a": "Nantes",
    "entity_b": "Toulouse",
    "venue": "Stade de la Beaujoire",
    "a_win_prob": 23.1,
    "draw_prob": 17.9,
    "b_win_prob": 59.0,
    "prediction": "Away Win",
    "actual_result": "Not Played",
    "score_a": null,
    "score_b": null,
    "is_correct": null,
    "confidence": 59.0,
    "confidence_level": "Medium",
    "elo_a": 1486,
    "elo_b": 1512.74,
    "elo_diff": -27,
    "colley_a": 1220,
    "colley_b": 1669,
    "form_a": 0.0,
    "form_b": 100.0,
    "odds_available": false,
    "sources": {
      "elo": {
        "a": 42.3,
        "d": 23.7,
        "b": 34.0
      },
      "colley": {
        "a": 8.7,
        "d": 12.0,
        "b": 79.3
      },
      "form": {
        "a": 0.3,
        "d": 12.0,
        "b": 87.7
      },
      "odds": null
    },
    "weights_used": {
      "elo": 0.5,
      "colley": 0.2142857142857143,
      "form": 0.28571428571428575,
      "odds": 0.0
    },
    "day_of_week": "Sunday",
    "week_number": 20,
    "year": 2026,
    "month": 5
  },
  {
    "id": 7,
    "date": "2026-05-17 19:00",
    "time": "19:00",
    "entity_a": "Nice",
    "entity_b": "Metz",
    "venue": "Allianz Riviera",
    "a_win_prob": 44.0,
    "draw_prob": 23.0,
    "b_win_prob": 33.0,
    "prediction": "Home Win",
    "actual_result": "Not Played",
    "score_a": null,
    "score_b": null,
    "is_correct": null,
    "confidence": 44.0,
    "confidence_level": "Low",
    "elo_a": 1488.940080706437,
    "elo_b": 1482.47500496,
    "elo_diff": 6,
    "colley_a": 1279,
    "colley_b": 1279,
    "form_a": 0.0,
    "form_b": 0.0,
    "odds_available": false,
    "sources": {
      "elo": {
        "a": 47.1,
        "d": 21.7,
        "b": 31.2
      },
      "colley": {
        "a": 46.2,
        "d": 22.1,
        "b": 31.7
      },
      "form": {
        "a": 37.0,
        "d": 26.0,
        "b": 37.0
      },
      "odds": null
    },
    "weights_used": {
      "elo": 0.5,
      "colley": 0.2142857142857143,
      "form": 0.28571428571428575,
      "odds": 0.0
    },
    "day_of_week": "Sunday",
    "week_number": 20,
    "year": 2026,
    "month": 5
  },
  {
    "id": 8,
    "date": "2026-05-17 19:00",
    "time": "19:00",
    "entity_a": "Paris FC",
    "entity_b": "PSG",
    "venue": "Stade Jean Bouin",
    "a_win_prob": 21.7,
    "draw_prob": 18.2,
    "b_win_prob": 60.1,
    "prediction": "Away Win",
    "actual_result": "Not Played",
    "score_a": null,
    "score_b": null,
    "is_correct": null,
    "confidence": 60.1,
    "confidence_level": "Medium",
    "elo_a": 1487.5148,
    "elo_b": 1526.353376,
    "elo_diff": -39,
    "colley_a": 1279,
    "colley_b": 1800,
    "form_a": 0.0,
    "form_b": 100.0,
    "odds_available": false,
    "sources": {
      "elo": {
        "a": 40.6,
        "d": 24.4,
        "b": 35.0
      },
      "colley": {
        "a": 5.9,
        "d": 12.0,
        "b": 82.1
      },
      "form": {
        "a": 0.3,
        "d": 12.0,
        "b": 87.7
      },
      "odds": null
    },
    "weights_used": {
      "elo": 0.5,
      "colley": 0.2142857142857143,
      "form": 0.28571428571428575,
      "odds": 0.0
    },
    "day_of_week": "Sunday",
    "week_number": 20,
    "year": 2026,
    "month": 5
  },
  {
    "id": 9,
    "date": "2026-05-17 19:00",
    "time": "19:00",
    "entity_a": "Strasbourg",
    "entity_b": "Monaco",
    "venue": "Stade de la Meinau",
    "a_win_prob": 67.3,
    "draw_prob": 16.0,
    "b_win_prob": 16.7,
    "prediction": "Home Win",
    "actual_result": "Not Played",
    "score_a": null,
    "score_b": null,
    "is_correct": null,
    "confidence": 67.3,
    "confidence_level": "Medium",
    "elo_a": 1517.362510664934,
    "elo_b": 1483.1689947635841,
    "elo_diff": 34,
    "colley_a": 1612,
    "colley_b": 1279,
    "form_a": 66.7,
    "form_b": 0.0,
    "odds_available": false,
    "sources": {
      "elo": {
        "a": 51.1,
        "d": 20.0,
        "b": 28.9
      },
      "colley": {
        "a": 79.9,
        "d": 12.0,
        "b": 8.1
      },
      "form": {
        "a": 86.1,
        "d": 12.0,
        "b": 1.9
      },
      "odds": null
    },
    "weights_used": {
      "elo": 0.5,
      "colley": 0.2142857142857143,
      "form": 0.28571428571428575,
      "odds": 0.0
    },
    "day_of_week": "Sunday",
    "week_number": 20,
    "year": 2026,
    "month": 5
  }
]