[
  {
    "name": "Gotham",
    "matches": 25,
    "wins": 12,
    "draws": 8,
    "losses": 5,
    "score_for": 31,
    "score_against": 17,
    "score_diff": 14,
    "points": 44,
    "home_wins": 4,
    "home_draws": 7,
    "home_losses": 2,
    "away_wins": 8,
    "away_draws": 1,
    "away_losses": 3,
    "form": "WWDLD",
    "win_rate": 48.0,
    "type": "team",
    "position": 1,
    "rating": 1510.2091562709816,
    "colley_rating": 1744
  },
  {
    "name": "Kansas City",
    "matches": 23,
    "wins": 14,
    "draws": 2,
    "losses": 7,
    "score_for": 33,
    "score_against": 21,
    "score_diff": 12,
    "points": 44,
    "home_wins": 9,
    "home_draws": 2,
    "home_losses": 1,
    "away_wins": 5,
    "away_draws": 0,
    "away_losses": 6,
    "form": "WWWDW",
    "win_rate": 60.9,
    "type": "team",
    "position": 2,
    "rating": 1550.7302488,
    "colley_rating": 1800
  },
  {
    "name": "Portland",
    "matches": 26,
    "wins": 13,
    "draws": 5,
    "losses": 8,
    "score_for": 35,
    "score_against": 28,
    "score_diff": 7,
    "points": 44,
    "home_wins": 8,
    "home_draws": 2,
    "home_losses": 2,
    "away_wins": 5,
    "away_draws": 3,
    "away_losses": 6,
    "form": "LLDWL",
    "win_rate": 50.0,
    "type": "team",
    "position": 3,
    "rating": 1494.352848,
    "colley_rating": 1682
  },
  {
    "name": "Washington",
    "matches": 26,
    "wins": 11,
    "draws": 10,
    "losses": 5,
    "score_for": 40,
    "score_against": 24,
    "score_diff": 16,
    "points": 43,
    "home_wins": 7,
    "home_draws": 4,
    "home_losses": 3,
    "away_wins": 4,
    "away_draws": 6,
    "away_losses": 2,
    "form": "DWDDW",
    "win_rate": 42.3,
    "type": "team",
    "position": 4,
    "rating": 1529.176952,
    "colley_rating": 1729
  },
  {
    "name": "Utah",
    "matches": 23,
    "wins": 11,
    "draws": 7,
    "losses": 5,
    "score_for": 31,
    "score_against": 20,
    "score_diff": 11,
    "points": 40,
    "home_wins": 6,
    "home_draws": 1,
    "home_losses": 3,
    "away_wins": 5,
    "away_draws": 6,
    "away_losses": 2,
    "form": "WDDLD",
    "win_rate": 47.8,
    "type": "team",
    "position": 5,
    "rating": 1508.6435999999999,
    "colley_rating": 1720
  },
  {
    "name": "San Diego",
    "matches": 25,
    "wins": 10,
    "draws": 5,
    "losses": 10,
    "score_for": 33,
    "score_against": 31,
    "score_diff": 2,
    "points": 35,
    "home_wins": 4,
    "home_draws": 1,
    "home_losses": 6,
    "away_wins": 6,
    "away_draws": 4,
    "away_losses": 4,
    "form": "DLWDD",
    "win_rate": 40.0,
    "type": "team",
    "position": 6,
    "rating": 1486.28,
    "colley_rating": 1519
  },
  {
    "name": "North Carolina",
    "matches": 23,
    "wins": 8,
    "draws": 8,
    "losses": 7,
    "score_for": 34,
    "score_against": 31,
    "score_diff": 3,
    "points": 32,
    "home_wins": 4,
    "home_draws": 5,
    "home_losses": 3,
    "away_wins": 4,
    "away_draws": 3,
    "away_losses": 4,
    "form": "LDDLD",
    "win_rate": 34.8,
    "type": "team",
    "position": 7,
    "rating": 1486.28,
    "colley_rating": 1541
  },
  {
    "name": "Houston",
    "matches": 23,
    "wins": 8,
    "draws": 6,
    "losses": 9,
    "score_for": 26,
    "score_against": 34,
    "score_diff": -8,
    "points": 30,
    "home_wins": 5,
    "home_draws": 4,
    "home_losses": 2,
    "away_wins": 3,
    "away_draws": 2,
    "away_losses": 7,
    "form": "DDWWD",
    "win_rate": 34.8,
    "type": "team",
    "position": 8,
    "rating": 1527,
    "colley_rating": 1487
  },
  {
    "name": "Orlando",
    "matches": 25,
    "wins": 7,
    "draws": 8,
    "losses": 10,
    "score_for": 29,
    "score_against": 34,
    "score_diff": -5,
    "points": 29,
    "home_wins": 4,
    "home_draws": 5,
    "home_losses": 5,
    "away_wins": 3,
    "away_draws": 3,
    "away_losses": 5,
    "form": "LLDDD",
    "win_rate": 28.0,
    "type": "team",
    "position": 9,
    "rating": 1478.8712,
    "colley_rating": 1417
  },
  {
    "name": "Seattle",
    "matches": 23,
    "wins": 7,
    "draws": 8,
    "losses": 8,
    "score_for": 22,
    "score_against": 29,
    "score_diff": -7,
    "points": 29,
    "home_wins": 5,
    "home_draws": 4,
    "home_losses": 3,
    "away_wins": 2,
    "away_draws": 4,
    "away_losses": 5,
    "form": "LDDDL",
    "win_rate": 30.4,
    "type": "team",
    "position": 10,
    "rating": 1486.6600358059175,
    "colley_rating": 1508
  },
  {
    "name": "Angel City",
    "matches": 21,
    "wins": 7,
    "draws": 4,
    "losses": 10,
    "score_for": 25,
    "score_against": 25,
    "score_diff": 0,
    "points": 25,
    "home_wins": 6,
    "home_draws": 1,
    "home_losses": 5,
    "away_wins": 1,
    "away_draws": 3,
    "away_losses": 5,
    "form": "LWWDD",
    "win_rate": 33.3,
    "type": "team",
    "position": 11,
    "rating": 1500.8858423808638,
    "colley_rating": 1413
  },
  {
    "name": "Louisville",
    "matches": 23,
    "wins": 6,
    "draws": 7,
    "losses": 10,
    "score_for": 32,
    "score_against": 34,
    "score_diff": -2,
    "points": 25,
    "home_wins": 4,
    "home_draws": 3,
    "home_losses": 2,
    "away_wins": 2,
    "away_draws": 4,
    "away_losses": 8,
    "form": "LDWDD",
    "win_rate": 26.1,
    "type": "team",
    "position": 12,
    "rating": 1504.3406276662338,
    "colley_rating": 1412
  },
  {
    "name": "Chicago",
    "matches": 22,
    "wins": 4,
    "draws": 7,
    "losses": 11,
    "score_for": 25,
    "score_against": 48,
    "score_diff": -23,
    "points": 19,
    "home_wins": 4,
    "home_draws": 4,
    "home_losses": 3,
    "away_wins": 0,
    "away_draws": 3,
    "away_losses": 8,
    "form": "WDDDD",
    "win_rate": 18.2,
    "type": "team",
    "position": 13,
    "rating": 1491.0121991242368,
    "colley_rating": 1278
  },
  {
    "name": "Bay",
    "matches": 22,
    "wins": 3,
    "draws": 7,
    "losses": 12,
    "score_for": 20,
    "score_against": 37,
    "score_diff": -17,
    "points": 16,
    "home_wins": 1,
    "home_draws": 4,
    "home_losses": 7,
    "away_wins": 2,
    "away_draws": 3,
    "away_losses": 5,
    "form": "LLLDD",
    "win_rate": 13.6,
    "type": "team",
    "position": 14,
    "rating": 1452,
    "colley_rating": 1200
  },
  {
    "name": "Denver",
    "matches": 9,
    "wins": 3,
    "draws": 3,
    "losses": 3,
    "score_for": 15,
    "score_against": 11,
    "score_diff": 4,
    "points": 12,
    "home_wins": 1,
    "home_draws": 1,
    "home_losses": 1,
    "away_wins": 2,
    "away_draws": 2,
    "away_losses": 2,
    "form": "DDWDL",
    "win_rate": 33.3,
    "type": "team",
    "position": 15,
    "rating": 1499.7238243317481,
    "colley_rating": 1478
  },
  {
    "name": "Boston",
    "matches": 11,
    "wins": 2,
    "draws": 3,
    "losses": 6,
    "score_for": 11,
    "score_against": 18,
    "score_diff": -7,
    "points": 9,
    "home_wins": 2,
    "home_draws": 1,
    "home_losses": 4,
    "away_wins": 0,
    "away_draws": 2,
    "away_losses": 2,
    "form": "LLLLL",
    "win_rate": 18.2,
    "type": "team",
    "position": 16,
    "rating": 1492.9711635375777,
    "colley_rating": 1221
  }
]